zimscan/__init__.py
zimscan/file.py
zimscan/reader.py
zimscan/record.py
zimscan-0.2.0.dist-info/LICENSE
zimscan-0.2.0.dist-info/METADATA
zimscan-0.2.0.dist-info/WHEEL
zimscan-0.2.0.dist-info/RECORD
