Metadata-Version: 2.1
Name: zimscan
Version: 0.2.0
Summary: ZIM file iterator
Home-page: https://github.com/jojolebarjos/zimscan
License: MIT
Keywords: zim,iterator,wikipedia,gutenberg,kiwix
Author: Johan Berdat
Author-email: jojolebarjos@gmail.com
Requires-Python: >=3.6,<4.0
Classifier: Development Status :: 4 - Beta
Classifier: Intended Audience :: Developers
Classifier: License :: OSI Approved :: MIT License
Classifier: Operating System :: OS Independent
Classifier: Programming Language :: Python :: 3
Classifier: Programming Language :: Python :: 3.6
Classifier: Programming Language :: Python :: 3.7
Classifier: Programming Language :: Python :: 3.8
Classifier: Programming Language :: Python :: 3.9
Classifier: Programming Language :: Python :: 3.10
Classifier: Programming Language :: Python :: 3.11
Classifier: Topic :: Software Development :: Libraries
Classifier: Topic :: Software Development :: Libraries :: Python Modules
Classifier: Topic :: Text Processing
Classifier: Topic :: Utilities
Requires-Dist: numpy (>=1.18,<2.0)
Requires-Dist: zstandard (>=0.16.0)
Project-URL: Repository, https://github.com/jojolebarjos/zimscan
